multi_demangle-1.0.1.dist-info/METADATA
multi_demangle-1.0.1.dist-info/WHEEL
multi_demangle-1.0.1.dist-info/licenses/LICENSE
multi_demangle.libs/libgcc_s-27e5a392.so.1
multi_demangle.libs/libstdc++-00b1837f.so.6
multi_demangle/__init__.py
multi_demangle/multi_demangle.cpython-312-i386-linux-musl.so
multi_demangle-1.0.1.dist-info/RECORD
