Metadata-Version: 2.4
Name: multi-demangle
Version: 1.0.1
Classifier: Programming Language :: Rust
Classifier: Programming Language :: Python :: Implementation :: CPython
Classifier: Programming Language :: Python :: Implementation :: PyPy
License-File: LICENSE
Summary: A library to demangle symbols from various languages and compilers.
Home-Page: 
Author-email: Team AppThreat <cloud@appthreat.com>
License: MIT
Requires-Python: >=3.10
